Metadata-Version: 1.0
Name: bookmark-config
Version: 1.1.0
Summary: Python module for fetching configuration values for Bookmark services.
Home-page: https://github.com/Bookmark-Novels/Bookmark-Config
Author: Bookmark Novels
Author-email: UNKNOWN
License: MIT
Platform: UNKNOWN
